upload_py/__init__.py
upload_py/example.py
upload.py-0.24.dist-info/LICENSE
upload.py-0.24.dist-info/METADATA
upload.py-0.24.dist-info/WHEEL
upload.py-0.24.dist-info/top_level.txt
upload.py-0.24.dist-info/RECORD
