Metadata-Version: 2.1
Name: upload.py
Version: 0.24
Summary: An mutiple upload service library
Home-page: https://github.com/CrafterPika/upload.py
Author: upload.py
Author-email: crafterpika@email.com
License: The Unlicense
Platform: UNKNOWN
Classifier: Programming Language :: Python :: 3
Classifier: Programming Language :: Python :: 3.4
Classifier: Programming Language :: Python :: 3.8
Requires-Dist: requests
Requires-Dist: BeautifulSoup4
